aiohubspace/__init__.py
aiohubspace/anonomyize_data.py
aiohubspace/device.py
aiohubspace/errors.py
aiohubspace/types.py
aiohubspace/util.py
aiohubspace/v1/__init__.py
aiohubspace/v1/auth.py
aiohubspace/v1/v1_const.py
aiohubspace/v1/controllers/__init__.py
aiohubspace/v1/controllers/base.py
aiohubspace/v1/controllers/device.py
aiohubspace/v1/controllers/event.py
aiohubspace/v1/controllers/fan.py
aiohubspace/v1/controllers/light.py
aiohubspace/v1/controllers/lock.py
aiohubspace/v1/controllers/switch.py
aiohubspace/v1/controllers/valve.py
aiohubspace/v1/models/__init__.py
aiohubspace/v1/models/device.py
aiohubspace/v1/models/fan.py
aiohubspace/v1/models/features.py
aiohubspace/v1/models/light.py
aiohubspace/v1/models/lock.py
aiohubspace/v1/models/resource.py
aiohubspace/v1/models/sensor.py
aiohubspace/v1/models/switch.py
aiohubspace/v1/models/valve.py
aiohubspace-1.2.0.dist-info/METADATA
aiohubspace-1.2.0.dist-info/WHEEL
aiohubspace-1.2.0.dist-info/licenses/LICENSE.txt
aiohubspace-1.2.0.dist-info/RECORD
